wink_sdk_extranet_booking/__init__.py
wink_sdk_extranet_booking/api_client.py
wink_sdk_extranet_booking/api_response.py
wink_sdk_extranet_booking/configuration.py
wink_sdk_extranet_booking/exceptions.py
wink_sdk_extranet_booking/py.typed
wink_sdk_extranet_booking/rest.py
wink_sdk_extranet_booking/api/__init__.py
wink_sdk_extranet_booking/api/analytics_api.py
wink_sdk_extranet_booking/api/booking_api.py
wink_sdk_extranet_booking/api/calendar_sync_api.py
wink_sdk_extranet_booking/api/consumer_booking_api.py
wink_sdk_extranet_booking/api/property_booking_api.py
wink_sdk_extranet_booking/api/review_api.py
wink_sdk_extranet_booking/api/test_booking_api.py
wink_sdk_extranet_booking/models/__init__.py
wink_sdk_extranet_booking/models/address_supplier.py
wink_sdk_extranet_booking/models/address_supplier_details.py
wink_sdk_extranet_booking/models/aggregate_descriptor_supplier.py
wink_sdk_extranet_booking/models/authenticated_user_supplier.py
wink_sdk_extranet_booking/models/authenticated_user_supplier_details.py
wink_sdk_extranet_booking/models/auto_base_unit_steps_supplier.py
wink_sdk_extranet_booking/models/axis_line_supplier.py
wink_sdk_extranet_booking/models/axis_ticks_supplier.py
wink_sdk_extranet_booking/models/bed_supplier.py
wink_sdk_extranet_booking/models/bed_supplier_details.py
wink_sdk_extranet_booking/models/bedroom_configuration_supplier.py
wink_sdk_extranet_booking/models/bedroom_configuration_supplier_details.py
wink_sdk_extranet_booking/models/bedroom_supplier.py
wink_sdk_extranet_booking/models/bedroom_supplier_details.py
wink_sdk_extranet_booking/models/beneficiary_charge_supplier.py
wink_sdk_extranet_booking/models/beneficiary_charge_supplier_details.py
wink_sdk_extranet_booking/models/beneficiary_supplier.py
wink_sdk_extranet_booking/models/beneficiary_supplier_details.py
wink_sdk_extranet_booking/models/booking_analytics_supplier.py
wink_sdk_extranet_booking/models/booking_ancillary_supplier.py
wink_sdk_extranet_booking-0.0.57.dist-info/licenses/LICENSE
wink_sdk_extranet_booking-0.0.57.dist-info/METADATA
wink_sdk_extranet_booking-0.0.57.dist-info/WHEEL
wink_sdk_extranet_booking-0.0.57.dist-info/top_level.txt
wink_sdk_extranet_booking-0.0.57.dist-info/RECORD
